main.py
wassup_my_g-0.0.2.dist-info/METADATA
wassup_my_g-0.0.2.dist-info/WHEEL
wassup_my_g-0.0.2.dist-info/top_level.txt
wassup_my_g-0.0.2.dist-info/RECORD
