Metadata-Version: 2.1
Name: wassup-my-g
Version: 0.0.2
Summary: The most useless package ever.
Author: Shefki Berisha
Author-email: mastibeatz16@gmail.com
